faviorm/__init__.py
faviorm/column.py
faviorm/database.py
faviorm/isql_struct.py
faviorm/table.py
faviorm-0.0.2.dist-info/METADATA
faviorm-0.0.2.dist-info/WHEEL
faviorm-0.0.2.dist-info/top_level.txt
faviorm-0.0.2.dist-info/RECORD
