Metadata-Version: 2.1
Name: faviorm
Version: 0.0.2
Summary: ASGI webserver
Author: Vladimir Vojtenko
Author-email: vladimirdev635@gmail.com
License: MIT
